PMAgg/__init__.py
PMAgg/unit_test.py
PMAgg/icons/X_axis.png
PMAgg/icons/Y_axis.png
PMAgg/icons/Z_axis.png
PMAgg/icons/annotation.png
PMAgg/icons/arrow.png
PMAgg/icons/axis.png
PMAgg/icons/back.png
PMAgg/icons/colorbar.png
PMAgg/icons/figure.png
PMAgg/icons/front.png
PMAgg/icons/grid.png
PMAgg/icons/home.png
PMAgg/icons/image.png
PMAgg/icons/layout.png
PMAgg/icons/legend.png
PMAgg/icons/line.png
PMAgg/icons/oval.png
PMAgg/icons/pan.png
PMAgg/icons/point.png
PMAgg/icons/polygon.png
PMAgg/icons/rect.png
PMAgg/icons/rotate.png
PMAgg/icons/save.png
PMAgg/icons/science.png
PMAgg/icons/setting.png
PMAgg/icons/space.png
PMAgg/icons/style.png
PMAgg/icons/text.png
PMAgg/icons/zoom.png
PMAgg/langs/en_axes_control.qm
PMAgg/langs/en_pmagg_ui.qm
PMAgg/langs/zh_CN_axes_control.qm
PMAgg/langs/zh_CN_pmagg_ui.qm
PMAgg/ui/__init__.py
PMAgg/ui/arrow_setting.py
PMAgg/ui/axes_control.py
PMAgg/ui/axis_edit.py
PMAgg/ui/axis_edit_manager.py
PMAgg/ui/color_table.py
PMAgg/ui/colorbar_setting.py
PMAgg/ui/default_setting.py
PMAgg/ui/default_setting_manager.py
PMAgg/ui/ellipse_setting.py
PMAgg/ui/image_setting.py
PMAgg/ui/legend_setting.py
PMAgg/ui/line2d_setting.py
PMAgg/ui/linestyles.py
PMAgg/ui/pmagg_ui.py
PMAgg/ui/rectangle_setting.py
PMAgg/ui/save_image_setting.py
PMAgg/ui/text_setting.py
PMAgg/ui/title_setting.py
PMAgg-1.0.0.dist-info/LICENSE
PMAgg-1.0.0.dist-info/METADATA
PMAgg-1.0.0.dist-info/WHEEL
PMAgg-1.0.0.dist-info/top_level.txt
PMAgg-1.0.0.dist-info/RECORD
