Metadata-Version: 2.1
Name: PMAgg
Version: 1.0.0
Summary: A matplotlib GUI backend with interactive capabilities
Home-page: https://gitee.com/lvvl/pmagg
Author: jcl
Author-email: 2195932461@qq.com
License: UNKNOWN
Platform: UNKNOWN
Classifier: Programming Language :: Python :: 3
Classifier: License :: OSI Approved :: MIT License
Classifier: Operating System :: OS Independent
Requires-Python: >=3.5
Requires-Dist: PySide2
Requires-Dist: matplotlib
